cross/__init__.py
cross/exceptions.py
cross/protocols.py
cross/py.typed
cross/response.py
cross/request/__init__.py
cross/request/_aiohttp.py
cross/request/_base.py
cross/request/_chalice.py
cross/request/_django.py
cross/request/_flask.py
cross/request/_litestar.py
cross/request/_quart.py
cross/request/_sanic.py
cross/request/_starlette.py
cross/request/_testing.py
cross_web-0.2.3.dist-info/METADATA
cross_web-0.2.3.dist-info/WHEEL
cross_web-0.2.3.dist-info/licenses/LICENSE
cross_web-0.2.3.dist-info/RECORD
