Metadata-Version: 2.4
Name: cross-web
Version: 0.2.3
Summary: A library for working with web frameworks
Author-email: Patrick Arminio <patrick.arminio@gmail.com>
License-File: LICENSE
Classifier: Development Status :: 5 - Production/Stable
Classifier: Intended Audience :: Developers
Classifier: License :: OSI Approved :: MIT License
Classifier: Topic :: Software Development :: Libraries
Classifier: Topic :: Software Development :: Libraries :: Python Modules
Requires-Python: >=3.9
Requires-Dist: typing-extensions>=4.14.0
